vhdl/mulop.vhdl
library ieee;
use ieee.numeric_std.ALL;
use ieee.std_logic_1164.ALL;

entity mulop is
    port
    (
        I_1 : in STD_LOGIC_VECTOR (15 downto 0);
        I_2 : in STD_LOGIC_VECTOR (15 downto 0);
        O_1 : out STD_LOGIC_VECTOR (15 downto 0)
    );
end mulop;

architecture behav of mulop is

    --define intermediate signals that hold multiplication,
    --division and modulo results
    signal tmp_mul_result : unsigned (32 downto 0);
    signal tmp_div_result : unsigned (16 downto 0);
    signal tmp_mod_result : unsigned (15 downto 0);

    begin
            
            mul_proc: process(I_1, I_2)
            --those two variables are used to check whether the inputs
            --are zeros or not and then preppending them to the input vector
            variable pI_1 : std_logic;
            variable pI_2 : std_logic;
            begin
                pI_1 := not(I_1(15) or I_1(14) or I_1(13) or I_1(12) or 
                            I_1(11) or I_1(10) or I_1(9) or I_1(8) or 
                            I_1(7) or I_1(6) or I_1(5) or I_1(4) or 
                            I_1(3) or I_1(2) or I_1(1) or I_1(0));
                pI_2 := not(I_2(15) or I_2(14) or I_2(13) or I_2(12) or 
                            I_2(11) or I_2(10) or I_2(9) or I_2(8) or 
                            I_2(7) or I_2(6) or I_2(5) or I_2(4) or 
                            I_2(3) or I_2(2) or I_2(1) or I_2(0));
                
                tmp_mul_result <= "*"(unsigned(pI_1 & I_1), unsigned(pI_2 & I_2))(32 downto 0);
            end process mul_proc;

            div_proc : process( tmp_mul_result )
            begin
                tmp_div_result <= tmp_mul_result(32 downto 16);
            end process ; -- div_proc

            mod_proc : process( tmp_mul_result )
            begin
                tmp_mod_result <= tmp_mul_result(15 downto 0);
            end process ; -- mod_proc

            output_proc : process( tmp_div_result,  tmp_mod_result)
            begin
                if tmp_mod_result >= tmp_div_result then
                    O_1 <= STD_LOGIC_VECTOR("-"(unsigned'(tmp_mod_result), tmp_div_result)(15 downto 0));
                else
                    O_1 <= STD_LOGIC_VECTOR("+"(unsigned'("-"(unsigned'(tmp_mod_result), tmp_div_result)), unsigned'("1" & x"0001"))(15 downto 0));
                end if;
            end process ; -- output_proc
    end behav;

vhdl/tb_mulop.vhdl
library ieee;
use ieee.numeric_std.ALL;
use ieee.std_logic_1164.ALL;

entity tb_mulop is
end tb_mulop;

architecture behav of tb_mulop is
    --component declaration
    component mulop
    port
    (
        I_1 : IN  STD_LOGIC_VECTOR(15 downto 0);
        I_2 : IN  STD_LOGIC_VECTOR(15 downto 0);
        O_1 : OUT  STD_LOGIC_VECTOR(15 downto 0)
    );
    END COMPONENT;

    --input signals
    signal I_1 : STD_LOGIC_VECTOR(15 downto 0) := (others => '0');
    signal I_2 : STD_LOGIC_VECTOR(15 downto 0) := (others => '0');

    --output signal
    signal O_1 : STD_LOGIC_VECTOR(15 downto 0);

begin
    --instantiation of mulop
    uut: mulop port map 
    (
        I_1 => I_1,
        I_2 => I_2,
        O_1 => O_1
    );

    stim_proc: process
    begin
        wait for 100 ns;
        I_1 <= x"0000";
        I_2 <= x"0000";
		  wait for 10 ns;
        assert (O_1 /= x"0001") report "vector not matched";
        wait for 100 ns;
        I_1 <= x"0001";
        I_2 <= x"0000";
        assert (O_1 /= x"0000") report "vector not matched";
        wait for 100 ns;
        I_1 <= x"0001";
        I_2 <= x"0001";
        assert (O_1 /= x"0001") report "vector not matched";
        wait for 100 ns;
        I_1 <= x"0003";
        I_2 <= x"0001";
        assert (O_1 /= x"0003") report "vector not matched";
        wait for 100 ns;
        I_1 <= x"0003";
        I_2 <= x"0003";
        assert (O_1 /= x"0009") report "vector not matched";
        wait for 100 ns;
        I_1 <= x"7fff";
        I_2 <= x"0003";
        assert (O_1 /= x"7ffc") report "vector not matched";
        wait for 100 ns;
        I_1 <= x"7fff";
        I_2 <= x"7fff";
        assert (O_1 /= x"c003") report "vector not matched";
        wait for 100 ns;
		  I_1 <= x"ffff";
        I_2 <= x"7fff";
        assert (O_1 /= x"0003") report "vector not matched";
		  I_1 <= x"ffff";
        I_2 <= x"ffff";
        assert (O_1 /= x"0004") report "vector not matched";
        wait for 100 ns;
        I_1 <= x"8000";
        I_2 <= x"ffff";
        assert (O_1 /= x"0001") report "vector not matched";
        wait for 100 ns;
        I_1 <= x"8000";
        I_2 <= x"8000";
        assert (O_1 /= x"c001") report "vector not matched";
        wait for 100 ns;
        I_1 <= x"ffff";
        I_2 <= x"ffff";
        assert (O_1 /= x"0004") report "vector not matched";

        assert false report "Reached end of test";
        wait;
    end process;
end behav;

vhdl/mulop.vcd
$date
  Mon May 17 00:35:02 2021
$end
$version
  GHDL v0
$end
$timescale
  1 fs
$end
$scope module standard $end
$upscope $end
$scope module std_logic_1164 $end
$upscope $end
$scope module numeric_std $end
$upscope $end
$scope module tb_mulop $end
$var reg 16 ! i_1[15:0] $end
$var reg 16 " i_2[15:0] $end
$var reg 16 # o_1[15:0] $end
$scope module uut $end
$var reg 16 $ i_1[15:0] $end
$var reg 16 % i_2[15:0] $end
$var reg 16 & o_1[15:0] $end
$var reg 33 ' tmp_mul_result[32:0] $end
$var reg 17 ( tmp_div_result[16:0] $end
$var reg 16 ) tmp_mod_result[15:0] $end
$upscope $end
$upscope $end
$enddefinitions $end
#0
b0000000000000000 !
b0000000000000000 "
b0000000000000001 #
b0000000000000000 $
b0000000000000000 %
b0000000000000001 &
b100000000000000000000000000000000 '
b10000000000000000 (
b0000000000000000 )
#100000000
#200000000
b0000000000000001 !
b0000000000000000 #
b0000000000000001 $
b0000000000000000 &
b000000000000000010000000000000000 '
b00000000000000001 (
#300000000
b0000000000000001 "
b0000000000000001 #
b0000000000000001 %
b0000000000000001 &
b000000000000000000000000000000001 '
b00000000000000000 (
b0000000000000001 )
#400000000
b0000000000000011 !
b0000000000000011 #
b0000000000000011 $
b0000000000000011 &
b000000000000000000000000000000011 '
b0000000000000011 )
#500000000
b0000000000000011 "
b0000000000001001 #
b0000000000000011 %
b0000000000001001 &
b000000000000000000000000000001001 '
b0000000000001001 )
#600000000
b0111111111111111 !
b0111111111111100 #
b0111111111111111 $
b0111111111111100 &
b000000000000000010111111111111101 '
b00000000000000001 (
b0111111111111101 )
#700000000
b0111111111111111 "
b1100000000000011 #
b0111111111111111 %
b1100000000000011 &
b000111111111111110000000000000001 '
b00011111111111111 (
b0000000000000001 )
#800000000
b1111111111111111 !
b1111111111111111 "
b0000000000000100 #
b1111111111111111 $
b1111111111111111 %
b0000000000000100 &
b011111111111111100000000000000001 '
b01111111111111110 (
#900000000
b1000000000000000 !
b0000000000000001 #
b1000000000000000 $
b0000000000000001 &
b001111111111111111000000000000000 '
b00111111111111111 (
b1000000000000000 )
#1000000000
b1000000000000000 "
b1100000000000001 #
b1000000000000000 %
b1100000000000001 &
b001000000000000000000000000000000 '
b00100000000000000 (
b0000000000000000 )
#1100000000
b1111111111111111 !
b1111111111111111 "
b0000000000000100 #
b1111111111111111 $
b1111111111111111 %
b0000000000000100 &
b011111111111111100000000000000001 '
b01111111111111110 (
b0000000000000001 )
