vhdl/xorop.vhdl
----------------------------------------------------------------------------------
-- Company: 
-- Engineer: 
-- 
-- Create Date:    11:52:47 05/07/2021 
-- Design Name: 
-- Module Name:    xorop - Behavioral 
-- Project Name: 
-- Target Devices: 
-- Tool versions: 
-- Description: 
--
-- Dependencies: 
--
-- Revision: 
-- Revision 0.01 - File Created
-- Additional Comments: 
--
----------------------------------------------------------------------------------
library IEEE;
use IEEE.STD_LOGIC_1164.ALL;

-- Uncomment the following library declaration if using
-- arithmetic functions with Signed or Unsigned values
use IEEE.NUMERIC_STD.ALL;

-- Uncomment the following library declaration if instantiating
-- any Xilinx primitives in this code.
--library UNISIM;
--use UNISIM.VComponents.all;

entity xorop is
    Port ( I_1 : in  STD_LOGIC_VECTOR (15 downto 0);
           I_2 : in  STD_LOGIC_VECTOR (15 downto 0);
           O_1 : out  STD_LOGIC_VECTOR (15 downto 0));
end xorop;

architecture Behavioral of xorop is

begin

	XOROP_proc: process(I_1, I_2)
	begin
		O_1 <= (I_1 xor I_2);
	end process XOROP_proc;

end Behavioral;

vhdl/addop.vhdl
LIBRARY IEEE;
USE ieee.std_logic_1164.ALL;
USE IEEE.numeric_std.ALL;

ENTITY addop IS
	PORT (
		I_1 : IN STD_LOGIC_VECTOR (15 DOWNTO 0);
		I_2 : IN STD_LOGIC_VECTOR (15 DOWNTO 0);
		O_1 : OUT STD_LOGIC_VECTOR (15 DOWNTO 0));
END addop;

ARCHITECTURE Behavioral OF addop IS
BEGIN
	ADDOP_proc : PROCESS (I_1, I_2)
	BEGIN
		O_1 <= STD_LOGIC_VECTOR("+"(unsigned(I_1), unsigned(I_2))(15 DOWNTO 0));
	END PROCESS ADDOP_proc;

END Behavioral;

vhdl/mulop.vhdl
library ieee;
use ieee.numeric_std.ALL;
use ieee.std_logic_1164.ALL;

entity mulop is
    port
    (
        I_1 : in STD_LOGIC_VECTOR (15 downto 0);
        I_2 : in STD_LOGIC_VECTOR (15 downto 0);
        O_1 : out STD_LOGIC_VECTOR (15 downto 0)
    );
end mulop;

architecture behav of mulop is

    --define intermediate signals that hold multiplication,
    --division and modulo results
    signal tmp_mul_result : unsigned (32 downto 0);
    signal tmp_div_result : unsigned (16 downto 0);
    signal tmp_mod_result : unsigned (15 downto 0);

    begin
            
            mul_proc: process(I_1, I_2)
            --those two variables are used to check whether the inputs
            --are zeros or not and then preppending them to the input vector
            variable pI_1 : std_logic;
            variable pI_2 : std_logic;
            begin
                pI_1 := not(I_1(15) or I_1(14) or I_1(13) or I_1(12) or 
                            I_1(11) or I_1(10) or I_1(9) or I_1(8) or 
                            I_1(7) or I_1(6) or I_1(5) or I_1(4) or 
                            I_1(3) or I_1(2) or I_1(1) or I_1(0));
                pI_2 := not(I_2(15) or I_2(14) or I_2(13) or I_2(12) or 
                            I_2(11) or I_2(10) or I_2(9) or I_2(8) or 
                            I_2(7) or I_2(6) or I_2(5) or I_2(4) or 
                            I_2(3) or I_2(2) or I_2(1) or I_2(0));
                
                tmp_mul_result <= "*"(unsigned(pI_1 & I_1), unsigned(pI_2 & I_2))(32 downto 0);
            end process mul_proc;

            div_proc : process( tmp_mul_result )
            begin
                tmp_div_result <= tmp_mul_result(32 downto 16);
            end process ; -- div_proc

            mod_proc : process( tmp_mul_result )
            begin
                tmp_mod_result <= tmp_mul_result(15 downto 0);
            end process ; -- mod_proc

            output_proc : process( tmp_div_result,  tmp_mod_result)
            begin
                if tmp_mod_result >= tmp_div_result then
                    O_1 <= STD_LOGIC_VECTOR("-"(unsigned'(tmp_mod_result), tmp_div_result)(15 downto 0));
                else
                    O_1 <= STD_LOGIC_VECTOR("+"(unsigned'("-"(unsigned'(tmp_mod_result), tmp_div_result)), unsigned'("1" & x"0001"))(15 downto 0));
                end if;
            end process ; -- output_proc
    end behav;

vhdl/round.vhdl
library ieee;
use ieee.numeric_std.all;
use ieee.std_logic_1164.all;

entity round is
    port (  X_1 : in STD_LOGIC_VECTOR (15 downto 0);
            X_2 : in STD_LOGIC_VECTOR (15 downto 0);
            X_3 : in STD_LOGIC_VECTOR (15 downto 0);
            X_4 : in STD_LOGIC_VECTOR (15 downto 0);
            Z_1 : in STD_LOGIC_VECTOR (15 downto 0);
            Z_2 : in STD_LOGIC_VECTOR (15 downto 0);
            Z_3 : in STD_LOGIC_VECTOR (15 downto 0);
            Z_4 : in STD_LOGIC_VECTOR (15 downto 0);
            Z_5 : in STD_LOGIC_VECTOR (15 downto 0);
            Z_6 : in STD_LOGIC_VECTOR (15 downto 0);
            Y_1 : out STD_LOGIC_VECTOR (15 downto 0);
            Y_2 : out STD_LOGIC_VECTOR (15 downto 0);
            Y_3 : out STD_LOGIC_VECTOR (15 downto 0);
            Y_4 : out STD_LOGIC_VECTOR (15 downto 0));
end round;

architecture Behavioral of round is

    --  Component Declaration for XOR, ADD, MUL
    --  XOR
    COMPONENT xorop
    PORT(
         I_1 : IN  STD_LOGIC_VECTOR(15 downto 0);
         I_2 : IN  STD_LOGIC_VECTOR(15 downto 0);
         O_1 : OUT  STD_LOGIC_VECTOR(15 downto 0)
        );
    END COMPONENT;
    --  ADD
    COMPONENT addop
    PORT(
         I_1 : IN  STD_LOGIC_VECTOR(15 downto 0);
         I_2 : IN  STD_LOGIC_VECTOR(15 downto 0);
         O_1 : OUT  STD_LOGIC_VECTOR(15 downto 0)
        );
    END COMPONENT;
    -- MUL
    COMPONENT mulop
    PORT(
         I_1 : IN  STD_LOGIC_VECTOR(15 downto 0);
         I_2 : IN  STD_LOGIC_VECTOR(15 downto 0);
         O_1 : OUT  STD_LOGIC_VECTOR(15 downto 0)
        );
    END COMPONENT;

    --signals
    --MUL
    signal MUL_1 : STD_LOGIC_VECTOR(15 downto 0);
    signal MUL_2 : STD_LOGIC_VECTOR(15 downto 0);
    signal MUL_3 : STD_LOGIC_VECTOR(15 downto 0);
    signal MUL_4 : STD_LOGIC_VECTOR(15 downto 0);
    --ADD
    signal ADD_1 : STD_LOGIC_VECTOR(15 downto 0);
    signal ADD_2 : STD_LOGIC_VECTOR(15 downto 0);
    signal ADD_3 : STD_LOGIC_VECTOR(15 downto 0);
    signal ADD_4 : STD_LOGIC_VECTOR(15 downto 0);
    --XOR
    signal XOR_1 : STD_LOGIC_VECTOR(15 downto 0);
    signal XOR_2 : STD_LOGIC_VECTOR(15 downto 0);
    begin
        --Instantiate MUL modules
        cMUL_1: mulop port map (I_1 => X_1, I_2 => Z_1, O_1 => MUL_1);
        cMUL_2: mulop port map (I_1 => X_4, I_2 => Z_4, O_1 => MUL_2);
        cMUL_3: mulop port map (I_1 => XOR_1, I_2 => Z_5, O_1 => MUL_3);
        cMUL_4: mulop port map (I_1 => ADD_3, I_2 => Z_6, O_1 => MUL_4);
        --Instantiate ADD modules
        cADD_1: addop port map (I_1 => X_2, I_2 => Z_2, O_1 => ADD_1);
        cADD_2: addop port map (I_1 => MUL_3, I_2 => MUL_4, O_1 => ADD_2);
        cADD_3: addop port map (I_1 => MUL_3, I_2 => XOR_2, O_1 => ADD_3);
        cADD_4: addop port map (I_1 => X_3, I_2 => Z_3, O_1 => ADD_4);
        --Instantiate XOR modules
        cXOR_1: xorop port map (I_1 => MUL_1, I_2 => ADD_4, O_1 => XOR_1);
        cXOR_2: xorop port map (I_1 => ADD_1, I_2 => MUL_2, O_1 => XOR_2);
        cXOR_3: xorop port map (I_1 => MUL_1, I_2 => MUL_4, O_1 => Y_1);
        cXOR_4: xorop port map (I_1 => MUL_4, I_2 => ADD_4, O_1 => Y_2);
        cXOR_5: xorop port map (I_1 => ADD_2, I_2 => ADD_1, O_1 => Y_3);
        cXOR_6: xorop port map (I_1 => MUL_2, I_2 => ADD_2, O_1 => Y_4);

end Behavioral;

vhdl/tb_round.vhdl
LIBRARY ieee;
USE ieee.std_logic_1164.ALL;
USE ieee.numeric_std.ALL;

ENTITY tb_round IS
END tb_round;
 
ARCHITECTURE behavior OF tb_round IS 
 
    -- Component Declaration for the Unit Under Test (UUT)
 
    COMPONENT round
        port (  X_1 : in STD_LOGIC_VECTOR (15 downto 0);
                X_2 : in STD_LOGIC_VECTOR (15 downto 0);
                X_3 : in STD_LOGIC_VECTOR (15 downto 0);
                X_4 : in STD_LOGIC_VECTOR (15 downto 0);
                Z_1 : in STD_LOGIC_VECTOR (15 downto 0);
                Z_2 : in STD_LOGIC_VECTOR (15 downto 0);
                Z_3 : in STD_LOGIC_VECTOR (15 downto 0);
                Z_4 : in STD_LOGIC_VECTOR (15 downto 0);
                Z_5 : in STD_LOGIC_VECTOR (15 downto 0);
                Z_6 : in STD_LOGIC_VECTOR (15 downto 0);
                Y_1 : out STD_LOGIC_VECTOR (15 downto 0);
                Y_2 : out STD_LOGIC_VECTOR (15 downto 0);
                Y_3 : out STD_LOGIC_VECTOR (15 downto 0);
                Y_4 : out STD_LOGIC_VECTOR (15 downto 0));
    END COMPONENT;
    

    --Inputs
    signal X_1 : STD_LOGIC_VECTOR (15 downto 0);
    signal X_2 : STD_LOGIC_VECTOR (15 downto 0);
    signal X_3 : STD_LOGIC_VECTOR (15 downto 0);
    signal X_4 : STD_LOGIC_VECTOR (15 downto 0);
    signal Z_1 : STD_LOGIC_VECTOR (15 downto 0);
    signal Z_2 : STD_LOGIC_VECTOR (15 downto 0);
    signal Z_3 : STD_LOGIC_VECTOR (15 downto 0);
    signal Z_4 : STD_LOGIC_VECTOR (15 downto 0);
    signal Z_5 : STD_LOGIC_VECTOR (15 downto 0);
    signal Z_6 : STD_LOGIC_VECTOR (15 downto 0);
    --outputs
    signal Y_1 : STD_LOGIC_VECTOR (15 downto 0);
    signal Y_2 : STD_LOGIC_VECTOR (15 downto 0);
    signal Y_3 : STD_LOGIC_VECTOR (15 downto 0);
    signal Y_4 : STD_LOGIC_VECTOR (15 downto 0);
  
BEGIN
 
	-- Instantiate the Unit Under Test (UUT)
   uut: round PORT MAP (
            X_1 => X_1,
            X_2 => X_2,
            X_3 => X_3,
            X_4 => X_4,
            Z_1 => Z_1,
            Z_2 => Z_2,
            Z_3 => Z_3,
            Z_4 => Z_4,
            Z_5 => Z_5,
            Z_6 => Z_6,
            Y_1 => Y_1,
            Y_2 => Y_2,
            Y_3 => Y_3,
            Y_4 => Y_4
        );

   -- Stimulus process
   stim_proc: process
   begin
        wait for 100 ns;		
        -- insert stimulus here 
        X_1 <= x"0000";
        X_2 <= x"0000";
        X_3 <= x"0000";
        X_4 <= x"0000";
        Z_1 <= x"0000";
        Z_2 <= x"0000";
        Z_3 <= x"0000";
        Z_4 <= x"0000";
        Z_5 <= x"0000";
        Z_6 <= x"0000";
        wait for 100 ns;
        X_1 <= x"ffff";
        X_2 <= x"0000";
        X_3 <= x"0000";
        X_4 <= x"0000";
        Z_1 <= x"0000";
        Z_2 <= x"0000";
        Z_3 <= x"0000";
        Z_4 <= x"0000";
        Z_5 <= x"0000";
        Z_6 <= x"0000";
        wait for 100 ns;
        X_1 <= x"ffff";
        X_2 <= x"aaaa";
        X_3 <= x"0000";
        X_4 <= x"0000";
        Z_1 <= x"0000";
        Z_2 <= x"0000";
        Z_3 <= x"0000";
        Z_4 <= x"0000";
        Z_5 <= x"0000";
        Z_6 <= x"0000";
        wait for 100 ns;
        X_1 <= x"ffff";
        X_2 <= x"aaaa";
        X_3 <= x"5555";
        X_4 <= x"0000";
        Z_1 <= x"0000";
        Z_2 <= x"0000";
        Z_3 <= x"0000";
        Z_4 <= x"0000";
        Z_5 <= x"0000";
        Z_6 <= x"0000";
        wait for 100 ns;
        X_1 <= x"ffff";
        X_2 <= x"aaaa";
        X_3 <= x"5555";
        X_4 <= x"2492";
        Z_1 <= x"0000";
        Z_2 <= x"0000";
        Z_3 <= x"0000";
        Z_4 <= x"0000";
        Z_5 <= x"0000";
        Z_6 <= x"0000";
        wait for 100 ns;
        X_1 <= x"ffff";
        X_2 <= x"aaaa";
        X_3 <= x"5555";
        X_4 <= x"2492";
        Z_1 <= x"db6d";
        Z_2 <= x"0000";
        Z_3 <= x"0000";
        Z_4 <= x"0000";
        Z_5 <= x"0000";
        Z_6 <= x"0000";
        wait for 100 ns;
        X_1 <= x"ffff";
        X_2 <= x"aaaa";
        X_3 <= x"5555";
        X_4 <= x"2492";
        Z_1 <= x"db6d";
        Z_2 <= x"1c71";
        Z_3 <= x"0000";
        Z_4 <= x"0000";
        Z_5 <= x"0000";
        Z_6 <= x"0000";
        wait for 100 ns;
        X_1 <= x"ffff";
        X_2 <= x"aaaa";
        X_3 <= x"5555";
        X_4 <= x"2492";
        Z_1 <= x"db6d";
        Z_2 <= x"1c71";
        Z_3 <= x"cccc";
        Z_4 <= x"0000";
        Z_5 <= x"0000";
        Z_6 <= x"0000";
        wait for 100 ns;
        X_1 <= x"ffff";
        X_2 <= x"aaaa";
        X_3 <= x"5555";
        X_4 <= x"2492";
        Z_1 <= x"db6d";
        Z_2 <= x"1c71";
        Z_3 <= x"cccc";
        Z_4 <= x"0002";
        Z_5 <= x"0000";
        Z_6 <= x"0000";
        wait for 100 ns;
        X_1 <= x"ffff";
        X_2 <= x"aaaa";
        X_3 <= x"5555";
        X_4 <= x"2492";
        Z_1 <= x"db6d";
        Z_2 <= x"1c71";
        Z_3 <= x"cccc";
        Z_4 <= x"0002";
        Z_5 <= x"eeee";
        Z_6 <= x"0000";
        wait for 100 ns;
        X_1 <= x"ffff";
        X_2 <= x"aaaa";
        X_3 <= x"5555";
        X_4 <= x"2492";
        Z_1 <= x"db6d";
        Z_2 <= x"1c71";
        Z_3 <= x"cccc";
        Z_4 <= x"0002";
        Z_5 <= x"eeee";
        Z_6 <= x"8888";
        wait for 100 ns;
        assert false report "reached the end of the test";
        wait for 100 ns;
        wait;
		
   end process;

END;

vhdl/round.vcd
$date
  Wed May 19 22:19:18 2021
$end
$version
  GHDL v0
$end
$timescale
  1 fs
$end
$scope module standard $end
$upscope $end
$scope module std_logic_1164 $end
$upscope $end
$scope module numeric_std $end
$upscope $end
$scope module tb_round $end
$var reg 16 ! x_1[15:0] $end
$var reg 16 " x_2[15:0] $end
$var reg 16 # x_3[15:0] $end
$var reg 16 $ x_4[15:0] $end
$var reg 16 % z_1[15:0] $end
$var reg 16 & z_2[15:0] $end
$var reg 16 ' z_3[15:0] $end
$var reg 16 ( z_4[15:0] $end
$var reg 16 ) z_5[15:0] $end
$var reg 16 * z_6[15:0] $end
$var reg 16 + y_1[15:0] $end
$var reg 16 , y_2[15:0] $end
$var reg 16 - y_3[15:0] $end
$var reg 16 . y_4[15:0] $end
$scope module uut $end
$var reg 16 / x_1[15:0] $end
$var reg 16 0 x_2[15:0] $end
$var reg 16 1 x_3[15:0] $end
$var reg 16 2 x_4[15:0] $end
$var reg 16 3 z_1[15:0] $end
$var reg 16 4 z_2[15:0] $end
$var reg 16 5 z_3[15:0] $end
$var reg 16 6 z_4[15:0] $end
$var reg 16 7 z_5[15:0] $end
$var reg 16 8 z_6[15:0] $end
$var reg 16 9 y_1[15:0] $end
$var reg 16 : y_2[15:0] $end
$var reg 16 ; y_3[15:0] $end
$var reg 16 < y_4[15:0] $end
$var reg 16 = mul_1[15:0] $end
$var reg 16 > mul_2[15:0] $end
$var reg 16 ? mul_3[15:0] $end
$var reg 16 @ mul_4[15:0] $end
$var reg 16 A add_1[15:0] $end
$var reg 16 B add_2[15:0] $end
$var reg 16 C add_3[15:0] $end
$var reg 16 D add_4[15:0] $end
$var reg 16 E xor_1[15:0] $end
$var reg 16 F xor_2[15:0] $end
$scope module cmul_1 $end
$var reg 16 G i_1[15:0] $end
$var reg 16 H i_2[15:0] $end
$var reg 16 I o_1[15:0] $end
$var reg 33 J tmp_mul_result[32:0] $end
$var reg 17 K tmp_div_result[16:0] $end
$var reg 16 L tmp_mod_result[15:0] $end
$upscope $end
$scope module cmul_2 $end
$var reg 16 M i_1[15:0] $end
$var reg 16 N i_2[15:0] $end
$var reg 16 O o_1[15:0] $end
$var reg 33 P tmp_mul_result[32:0] $end
$var reg 17 Q tmp_div_result[16:0] $end
$var reg 16 R tmp_mod_result[15:0] $end
$upscope $end
$scope module cmul_3 $end
$var reg 16 S i_1[15:0] $end
$var reg 16 T i_2[15:0] $end
$var reg 16 U o_1[15:0] $end
$var reg 33 V tmp_mul_result[32:0] $end
$var reg 17 W tmp_div_result[16:0] $end
$var reg 16 X tmp_mod_result[15:0] $end
$upscope $end
$scope module cmul_4 $end
$var reg 16 Y i_1[15:0] $end
$var reg 16 Z i_2[15:0] $end
$var reg 16 [ o_1[15:0] $end
$var reg 33 \ tmp_mul_result[32:0] $end
$var reg 17 ] tmp_div_result[16:0] $end
$var reg 16 ^ tmp_mod_result[15:0] $end
$upscope $end
$scope module cadd_1 $end
$var reg 16 _ i_1[15:0] $end
$var reg 16 ` i_2[15:0] $end
$var reg 16 a o_1[15:0] $end
$upscope $end
$scope module cadd_2 $end
$var reg 16 b i_1[15:0] $end
$var reg 16 c i_2[15:0] $end
$var reg 16 d o_1[15:0] $end
$upscope $end
$scope module cadd_3 $end
$var reg 16 e i_1[15:0] $end
$var reg 16 f i_2[15:0] $end
$var reg 16 g o_1[15:0] $end
$upscope $end
$scope module cadd_4 $end
$var reg 16 h i_1[15:0] $end
$var reg 16 i i_2[15:0] $end
$var reg 16 j o_1[15:0] $end
$upscope $end
$scope module cxor_1 $end
$var reg 16 k i_1[15:0] $end
$var reg 16 l i_2[15:0] $end
$var reg 16 m o_1[15:0] $end
$upscope $end
$scope module cxor_2 $end
$var reg 16 n i_1[15:0] $end
$var reg 16 o i_2[15:0] $end
$var reg 16 p o_1[15:0] $end
$upscope $end
$scope module cxor_3 $end
$var reg 16 q i_1[15:0] $end
$var reg 16 r i_2[15:0] $end
$var reg 16 s o_1[15:0] $end
$upscope $end
$scope module cxor_4 $end
$var reg 16 t i_1[15:0] $end
$var reg 16 u i_2[15:0] $end
$var reg 16 v o_1[15:0] $end
$upscope $end
$scope module cxor_5 $end
$var reg 16 w i_1[15:0] $end
$var reg 16 x i_2[15:0] $end
$var reg 16 y o_1[15:0] $end
$upscope $end
$scope module cxor_6 $end
$var reg 16 z i_1[15:0] $end
$var reg 16 { i_2[15:0] $end
$var reg 16 | o_1[15:0] $end
$upscope $end
$upscope $end
$upscope $end
$enddefinitions $end
#0
bUUUUUUUUUUUUUUUU !
bUUUUUUUUUUUUUUUU "
bUUUUUUUUUUUUUUUU #
bUUUUUUUUUUUUUUUU $
bUUUUUUUUUUUUUUUU %
bUUUUUUUUUUUUUUUU &
bUUUUUUUUUUUUUUUU '
bUUUUUUUUUUUUUUUU (
bUUUUUUUUUUUUUUUU )
bUUUUUUUUUUUUUUUU *
bXXXXXXXXXXXXXXXX +
bXXXXXXXXXXXXXXXX ,
bXXXXXXXXXXXXXXXX -
bXXXXXXXXXXXXXXXX .
bUUUUUUUUUUUUUUUU /
bUUUUUUUUUUUUUUUU 0
bUUUUUUUUUUUUUUUU 1
bUUUUUUUUUUUUUUUU 2
bUUUUUUUUUUUUUUUU 3
bUUUUUUUUUUUUUUUU 4
bUUUUUUUUUUUUUUUU 5
bUUUUUUUUUUUUUUUU 6
bUUUUUUUUUUUUUUUU 7
bUUUUUUUUUUUUUUUU 8
bXXXXXXXXXXXXXXXX 9
bXXXXXXXXXXXXXXXX :
bXXXXXXXXXXXXXXXX ;
bXXXXXXXXXXXXXXXX <
bXXXXXXXXXXXXXXXX =
bXXXXXXXXXXXXXXXX >
bXXXXXXXXXXXXXXXX ?
bXXXXXXXXXXXXXXXX @
bXXXXXXXXXXXXXXXX A
bXXXXXXXXXXXXXXXX B
bXXXXXXXXXXXXXXXX C
bXXXXXXXXXXXXXXXX D
bXXXXXXXXXXXXXXXX E
bXXXXXXXXXXXXXXXX F
bUUUUUUUUUUUUUUUU G
bUUUUUUUUUUUUUUUU H
bXXXXXXXXXXXXXXXX I
bXXXXXXXXXXXXXXXXXXXXXXXXXXXXXXXXX J
bXXXXXXXXXXXXXXXXX K
bXXXXXXXXXXXXXXXX L
bUUUUUUUUUUUUUUUU M
bUUUUUUUUUUUUUUUU N
bXXXXXXXXXXXXXXXX O
bXXXXXXXXXXXXXXXXXXXXXXXXXXXXXXXXX P
bXXXXXXXXXXXXXXXXX Q
bXXXXXXXXXXXXXXXX R
bXXXXXXXXXXXXXXXX S
bUUUUUUUUUUUUUUUU T
bXXXXXXXXXXXXXXXX U
bXXXXXXXXXXXXXXXXXXXXXXXXXXXXXXXXX V
bXXXXXXXXXXXXXXXXX W
bXXXXXXXXXXXXXXXX X
bXXXXXXXXXXXXXXXX Y
bUUUUUUUUUUUUUUUU Z
bXXXXXXXXXXXXXXXX [
bXXXXXXXXXXXXXXXXXXXXXXXXXXXXXXXXX \
bXXXXXXXXXXXXXXXXX ]
bXXXXXXXXXXXXXXXX ^
bUUUUUUUUUUUUUUUU _
bUUUUUUUUUUUUUUUU `
bXXXXXXXXXXXXXXXX a
bXXXXXXXXXXXXXXXX b
bXXXXXXXXXXXXXXXX c
bXXXXXXXXXXXXXXXX d
bXXXXXXXXXXXXXXXX e
bXXXXXXXXXXXXXXXX f
bXXXXXXXXXXXXXXXX g
bUUUUUUUUUUUUUUUU h
bUUUUUUUUUUUUUUUU i
bXXXXXXXXXXXXXXXX j
bXXXXXXXXXXXXXXXX k
bXXXXXXXXXXXXXXXX l
bXXXXXXXXXXXXXXXX m
bXXXXXXXXXXXXXXXX n
bXXXXXXXXXXXXXXXX o
bXXXXXXXXXXXXXXXX p
bXXXXXXXXXXXXXXXX q
bXXXXXXXXXXXXXXXX r
bXXXXXXXXXXXXXXXX s
bXXXXXXXXXXXXXXXX t
bXXXXXXXXXXXXXXXX u
bXXXXXXXXXXXXXXXX v
bXXXXXXXXXXXXXXXX w
bXXXXXXXXXXXXXXXX x
bXXXXXXXXXXXXXXXX y
bXXXXXXXXXXXXXXXX z
bXXXXXXXXXXXXXXXX {
bXXXXXXXXXXXXXXXX |
#100000000
b0000000000000000 !
b0000000000000000 "
b0000000000000000 #
b0000000000000000 $
b0000000000000000 %
b0000000000000000 &
b0000000000000000 '
b0000000000000000 (
b0000000000000000 )
b0000000000000000 *
b0000000000000001 +
b0000000000000000 ,
b0000000000000000 -
b0000000000000001 .
b0000000000000000 /
b0000000000000000 0
b0000000000000000 1
b0000000000000000 2
b0000000000000000 3
b0000000000000000 4
b0000000000000000 5
b0000000000000000 6
b0000000000000000 7
b0000000000000000 8
b0000000000000001 9
b0000000000000000 :
b0000000000000000 ;
b0000000000000001 <
b0000000000000001 =
b0000000000000001 >
b0000000000000000 ?
b0000000000000000 @
b0000000000000000 A
b0000000000000000 B
b0000000000000001 C
b0000000000000000 D
b0000000000000001 E
b0000000000000001 F
b0000000000000000 G
b0000000000000000 H
b0000000000000001 I
b100000000000000000000000000000000 J
b10000000000000000 K
b0000000000000000 L
b0000000000000000 M
b0000000000000000 N
b0000000000000001 O
b100000000000000000000000000000000 P
b10000000000000000 Q
b0000000000000000 R
b0000000000000001 S
b0000000000000000 T
b0000000000000000 U
b000000000000000010000000000000000 V
b00000000000000001 W
b0000000000000000 X
b0000000000000001 Y
b0000000000000000 Z
b0000000000000000 [
b000000000000000010000000000000000 \
b00000000000000001 ]
b0000000000000000 ^
b0000000000000000 _
b0000000000000000 `
b0000000000000000 a
b0000000000000000 b
b0000000000000000 c
b0000000000000000 d
b0000000000000000 e
b0000000000000001 f
b0000000000000001 g
b0000000000000000 h
b0000000000000000 i
b0000000000000000 j
b0000000000000001 k
b0000000000000000 l
b0000000000000001 m
b0000000000000000 n
b0000000000000001 o
b0000000000000001 p
b0000000000000001 q
b0000000000000000 r
b0000000000000001 s
b0000000000000000 t
b0000000000000000 u
b0000000000000000 v
b0000000000000000 w
b0000000000000000 x
b0000000000000000 y
b0000000000000001 z
b0000000000000000 {
b0000000000000001 |
#200000000
b1111111111111111 !
b0000000000000011 +
b0000000000000001 ,
b0000000000000000 -
b0000000000000001 .
b1111111111111111 /
b0000000000000011 9
b0000000000000001 :
b0000000000000000 ;
b0000000000000001 <
b0000000000000010 =
b1111111111111111 ?
b0000000000000001 @
b0000000000000000 B
b0000000000000000 C
b0000000000000010 E
b1111111111111111 G
b0000000000000010 I
b011111111111111110000000000000000 J
b01111111111111111 K
b0000000000000010 S
b1111111111111111 U
b000000000000000100000000000000000 V
b00000000000000010 W
b0000000000000000 Y
b0000000000000001 [
b100000000000000000000000000000000 \
b10000000000000000 ]
b1111111111111111 b
b0000000000000001 c
b0000000000000000 d
b1111111111111111 e
b0000000000000000 g
b0000000000000010 k
b0000000000000010 m
b0000000000000010 q
b0000000000000001 r
b0000000000000011 s
b0000000000000001 t
b0000000000000001 v
b0000000000000000 w
b0000000000000000 y
b0000000000000000 {
b0000000000000001 |
#300000000
b1010101010101010 "
b0101010101010101 +
b0101010101010111 ,
b1111111111111100 -
b0101010101010111 .
b1010101010101010 0
b0101010101010101 9
b0101010101010111 :
b1111111111111100 ;
b0101010101010111 <
b0101010101010111 @
b1010101010101010 A
b0101010101010110 B
b1010101010101010 C
b1010101010101011 F
b1010101010101010 Y
b0101010101010111 [
b010101010101010100000000000000000 \
b01010101010101010 ]
b1010101010101010 _
b1010101010101010 a
b0101010101010111 c
b0101010101010110 d
b1010101010101011 f
b1010101010101010 g
b1010101010101010 n
b1010101010101011 p
b0101010101010111 r
b0101010101010101 s
b0101010101010111 t
b0101010101010111 v
b0101010101010110 w
b1010101010101010 x
b1111111111111100 y
b0101010101010110 {
b0101010101010111 |
#400000000
b0101010101010101 #
b1010101010101110 +
b1111111111111001 ,
b1111111111111100 -
b0101010101010111 .
b0101010101010101 1
b1010101010101110 9
b1111111111111001 :
b1111111111111100 ;
b0101010101010111 <
b1010101010101010 ?
b1010101010101100 @
b0101010101010110 B
b0101010101010101 C
b0101010101010101 D
b0101010101010111 E
b0101010101010111 S
b1010101010101010 U
b001010101010101110000000000000000 V
b00101010101010111 W
b0101010101010101 Y
b1010101010101100 [
b001010101010101010000000000000000 \
b00101010101010101 ]
b1010101010101010 b
b1010101010101100 c
b0101010101010110 d
b1010101010101010 e
b0101010101010101 g
b0101010101010101 h
b0101010101010101 j
b0101010101010101 l
b0101010101010111 m
b1010101010101100 r
b1010101010101110 s
b1010101010101100 t
b0101010101010101 u
b1111111111111001 v
b0101010101010110 w
b1111111111111100 y
b0101010101010110 {
b0101010101010111 |
#500000000
b0010010010010010 $
b1110001110010000 +
b1011011011000111 ,
b0010010010010110 -
b0101010101010011 .
b0010010010010010 2
b1110001110010000 9
b1011011011000111 :
b0010010010010110 ;
b0101010101010011 <
b1101101101101111 >
b1110001110010010 @
b1000111000111100 B
b0001110001101111 C
b0111000111000101 F
b0010010010010010 M
b1101101101101111 O
b000100100100100100000000000000000 P
b00010010010010010 Q
b0001110001101111 Y
b1110001110010010 [
b000011100011011110000000000000000 \
b00001110001101111 ]
b1110001110010010 c
b1000111000111100 d
b0111000111000101 f
b0001110001101111 g
b1101101101101111 o
b0111000111000101 p
b1110001110010010 r
b1110001110010000 s
b1110001110010010 t
b1011011011000111 v
b1000111000111100 w
b0010010010010110 y
b1101101101101111 z
b1000111000111100 {
b0101010101010011 |
#600000000
b1101101101101101 %
b1110001110010000 +
b1111111111101101 ,
b0010010010010110 -
b0101010101010011 .
b1101101101101101 3
b1110001110010000 9
b1111111111101101 :
b0010010010010110 ;
b0101010101010011 <
b0100100100101000 =
b1110001110000100 ?
b1010101010111000 @
b1000111000111100 B
b0101010101001001 C
b0001110001111101 E
b1101101101101101 H
b0100100100101000 I
b011011011011011000010010010010011 J
b01101101101101100 K
b0010010010010011 L
b0001110001111101 S
b1110001110000100 U
b000011100011111010000000000000000 V
b00001110001111101 W
b0101010101001001 Y
b1010101010111000 [
b001010101010010010000000000000000 \
b00101010101001001 ]
b1110001110000100 b
b1010101010111000 c
b1000111000111100 d
b1110001110000100 e
b0101010101001001 g
b0100100100101000 k
b0001110001111101 m
b0100100100101000 q
b1010101010111000 r
b1110001110010000 s
b1010101010111000 t
b1111111111101101 v
b1000111000111100 w
b0010010010010110 y
b1000111000111100 {
b0101010101010011 |
#700000000
b0001110001110001 &
b0100100100100001 +
b0101010101011100 ,
b0010010010010110 -
b0011100011100010 .
b0001110001110001 4
b0100100100100001 9
b0101010101011100 :
b0010010010010110 ;
b0011100011100010 <
b0000000000001001 @
b1100011100011011 A
b1110001110001101 B
b1111111111111000 C
b0001110001110100 F
b1111111111111000 Y
b0000000000001001 [
b011111111111110000000000000000000 \
b01111111111111000 ]
b0001110001110001 `
b1100011100011011 a
b0000000000001001 c
b1110001110001101 d
b0001110001110100 f
b1111111111111000 g
b1100011100011011 n
b0001110001110100 p
b0000000000001001 r
b0100100100100001 s
b0000000000001001 t
b0101010101011100 v
b1110001110001101 w
b1100011100011011 x
b0010010010010110 y
b1110001110001101 {
b0011100011100010 |
#800000000
b1100110011001100 '
b0000011110111101 +
b0110110010110100 ,
b0010010010010110 -
b0011100011100010 .
b1100110011001100 5
b0000011110111101 9
b0110110010110100 :
b0010010010010110 ;
b0011100011100010 <
b1001010011111000 ?
b0100111010010101 @
b1110001110001101 B
b1011000101101100 C
b0010001000100001 D
b0110101100001001 E
b0110101100001001 S
b1001010011111000 U
b001101011000010010000000000000000 V
b00110101100001001 W
b1011000101101100 Y
b0100111010010101 [
b010110001011011000000000000000000 \
b01011000101101100 ]
b1001010011111000 b
b0100111010010101 c
b1110001110001101 d
b1001010011111000 e
b1011000101101100 g
b1100110011001100 i
b0010001000100001 j
b0010001000100001 l
b0110101100001001 m
b0100111010010101 r
b0000011110111101 s
b0100111010010101 t
b0010001000100001 u
b0110110010110100 v
b1110001110001101 w
b0010010010010110 y
b1110001110001101 {
b0011100011100010 |
