vhdl/addop.vhdl
LIBRARY IEEE;
USE ieee.std_logic_1164.ALL;
USE IEEE.numeric_std.ALL;

ENTITY addop IS
	PORT (
		I_1 : IN STD_LOGIC_VECTOR (15 DOWNTO 0);
		I_2 : IN STD_LOGIC_VECTOR (15 DOWNTO 0);
		O_1 : OUT STD_LOGIC_VECTOR (15 DOWNTO 0));
END addop;

ARCHITECTURE Behavioral OF addop IS
BEGIN
	ADDOP_proc : PROCESS (I_1, I_2)
	BEGIN
		O_1 <= STD_LOGIC_VECTOR("+"(unsigned(I_1), unsigned(I_2))(15 DOWNTO 0));
	END PROCESS ADDOP_proc;

END Behavioral;

vhdl/mulop.vhdl
library ieee;
use ieee.numeric_std.ALL;
use ieee.std_logic_1164.ALL;

entity mulop is
    port
    (
        I_1 : in STD_LOGIC_VECTOR (15 downto 0);
        I_2 : in STD_LOGIC_VECTOR (15 downto 0);
        O_1 : out STD_LOGIC_VECTOR (15 downto 0)
    );
end mulop;

architecture behav of mulop is

    --define intermediate signals that hold multiplication,
    --division and modulo results
    signal tmp_mul_result : unsigned (32 downto 0);
    signal tmp_div_result : unsigned (16 downto 0);
    signal tmp_mod_result : unsigned (15 downto 0);

    begin
            
            mul_proc: process(I_1, I_2)
            --those two variables are used to check whether the inputs
            --are zeros or not and then preppending them to the input vector
            variable pI_1 : std_logic;
            variable pI_2 : std_logic;
            begin
                pI_1 := not(I_1(15) or I_1(14) or I_1(13) or I_1(12) or 
                            I_1(11) or I_1(10) or I_1(9) or I_1(8) or 
                            I_1(7) or I_1(6) or I_1(5) or I_1(4) or 
                            I_1(3) or I_1(2) or I_1(1) or I_1(0));
                pI_2 := not(I_2(15) or I_2(14) or I_2(13) or I_2(12) or 
                            I_2(11) or I_2(10) or I_2(9) or I_2(8) or 
                            I_2(7) or I_2(6) or I_2(5) or I_2(4) or 
                            I_2(3) or I_2(2) or I_2(1) or I_2(0));
                
                tmp_mul_result <= "*"(unsigned(pI_1 & I_1), unsigned(pI_2 & I_2))(32 downto 0);
            end process mul_proc;

            div_proc : process( tmp_mul_result )
            begin
                tmp_div_result <= tmp_mul_result(32 downto 16);
            end process ; -- div_proc

            mod_proc : process( tmp_mul_result )
            begin
                tmp_mod_result <= tmp_mul_result(15 downto 0);
            end process ; -- mod_proc

            output_proc : process( tmp_div_result,  tmp_mod_result)
            begin
                if tmp_mod_result >= tmp_div_result then
                    O_1 <= STD_LOGIC_VECTOR("-"(unsigned'(tmp_mod_result), tmp_div_result)(15 downto 0));
                else
                    O_1 <= STD_LOGIC_VECTOR("+"(unsigned'("-"(unsigned'(tmp_mod_result), tmp_div_result)), unsigned'("1" & x"0001"))(15 downto 0));
                end if;
            end process ; -- output_proc
    end behav;

vhdl/trafo.vhdl
library ieee;
use ieee.numeric_std.all;
USE ieee.std_logic_1164.ALL;


entity trafo is
    port (  X_1 : in STD_LOGIC_VECTOR (15 downto 0);
            X_2 : in STD_LOGIC_VECTOR (15 downto 0);
            X_3 : in STD_LOGIC_VECTOR (15 downto 0);
            X_4 : in STD_LOGIC_VECTOR (15 downto 0);
            Z_1 : in STD_LOGIC_VECTOR (15 downto 0);
            Z_2 : in STD_LOGIC_VECTOR (15 downto 0);
            Z_3 : in STD_LOGIC_VECTOR (15 downto 0);
            Z_4 : in STD_LOGIC_VECTOR (15 downto 0);
            Y_1 : out STD_LOGIC_VECTOR (15 downto 0);
            Y_2 : out STD_LOGIC_VECTOR (15 downto 0);
            Y_3 : out STD_LOGIC_VECTOR (15 downto 0);
            Y_4 : out STD_LOGIC_VECTOR (15 downto 0));
end trafo;

architecture Behavioral of trafo is

    --  Component Declaration for ADD, MUL
    --  ADD
    COMPONENT addop
    PORT(
         I_1 : IN  STD_LOGIC_VECTOR(15 downto 0);
         I_2 : IN  STD_LOGIC_VECTOR(15 downto 0);
         O_1 : OUT  STD_LOGIC_VECTOR(15 downto 0)
        );
    END COMPONENT;
    -- MUL
    COMPONENT mulop
    PORT(
         I_1 : IN  STD_LOGIC_VECTOR(15 downto 0);
         I_2 : IN  STD_LOGIC_VECTOR(15 downto 0);
         O_1 : OUT  STD_LOGIC_VECTOR(15 downto 0)
        );
    END COMPONENT;

    --signals

    begin
        --Instantiate MUL modules
        cMUL_1: mulop port map (I_1 => X_1, I_2 => Z_1, O_1 => Y_1);
        cMUL_2: mulop port map (I_1 => X_4, I_2 => Z_4, O_1 => Y_4);
        --Instantiate ADD modules
        cADD_1: addop port map (I_1 => X_3, I_2 => Z_2, O_1 => Y_2);
        cADD_2: addop port map (I_1 => X_2, I_2 => Z_3, O_1 => Y_3);
        
end Behavioral;

vhdl/tb_trafo.vhdl
LIBRARY ieee;
USE ieee.std_logic_1164.ALL;
USE ieee.numeric_std.ALL;

ENTITY tb_trafo IS
END tb_trafo;
 
ARCHITECTURE behavior OF tb_trafo IS 
 
    -- Component Declaration for the Unit Under Test (UUT)
 
    COMPONENT trafo
        port (  X_1 : in STD_LOGIC_VECTOR (15 downto 0);
                X_2 : in STD_LOGIC_VECTOR (15 downto 0);
                X_3 : in STD_LOGIC_VECTOR (15 downto 0);
                X_4 : in STD_LOGIC_VECTOR (15 downto 0);
                Z_1 : in STD_LOGIC_VECTOR (15 downto 0);
                Z_2 : in STD_LOGIC_VECTOR (15 downto 0);
                Z_3 : in STD_LOGIC_VECTOR (15 downto 0);
                Z_4 : in STD_LOGIC_VECTOR (15 downto 0);
                Y_1 : out STD_LOGIC_VECTOR (15 downto 0);
                Y_2 : out STD_LOGIC_VECTOR (15 downto 0);
                Y_3 : out STD_LOGIC_VECTOR (15 downto 0);
                Y_4 : out STD_LOGIC_VECTOR (15 downto 0));
    END COMPONENT;
    

    --Inputs
    signal X_1 : STD_LOGIC_VECTOR (15 downto 0);
    signal X_2 : STD_LOGIC_VECTOR (15 downto 0);
    signal X_3 : STD_LOGIC_VECTOR (15 downto 0);
    signal X_4 : STD_LOGIC_VECTOR (15 downto 0);
    signal Z_1 : STD_LOGIC_VECTOR (15 downto 0);
    signal Z_2 : STD_LOGIC_VECTOR (15 downto 0);
    signal Z_3 : STD_LOGIC_VECTOR (15 downto 0);
    signal Z_4 : STD_LOGIC_VECTOR (15 downto 0);
    --outputs
    signal Y_1 : STD_LOGIC_VECTOR (15 downto 0);
    signal Y_2 : STD_LOGIC_VECTOR (15 downto 0);
    signal Y_3 : STD_LOGIC_VECTOR (15 downto 0);
    signal Y_4 : STD_LOGIC_VECTOR (15 downto 0);
  
BEGIN
 
	-- Instantiate the Unit Under Test (UUT)
   uut: trafo PORT MAP (
            X_1 => X_1,
            X_2 => X_2,
            X_3 => X_3,
            X_4 => X_4,
            Z_1 => Z_1,
            Z_2 => Z_2,
            Z_3 => Z_3,
            Z_4 => Z_4,
            Y_1 => Y_1,
            Y_2 => Y_2,
            Y_3 => Y_3,
            Y_4 => Y_4
        );

   -- Stimulus process
   stim_proc: process
   begin
        wait for 100 ns;		
        -- insert stimulus here 
        X_1 <= x"0000";
        X_2 <= x"0000";
        X_3 <= x"0000";
        X_4 <= x"0000";
        Z_1 <= x"0000";
        Z_2 <= x"0000";
        Z_3 <= x"0000";
        Z_4 <= x"0000";
        wait for 100 ns;
        X_1 <= x"ffff";
        X_2 <= x"0000";
        X_3 <= x"0000";
        X_4 <= x"0000";
        Z_1 <= x"0000";
        Z_2 <= x"0000";
        Z_3 <= x"0000";
        Z_4 <= x"0000";
        wait for 100 ns;
        X_1 <= x"ffff";
        X_2 <= x"aaaa";
        X_3 <= x"0000";
        X_4 <= x"0000";
        Z_1 <= x"0000";
        Z_2 <= x"0000";
        Z_3 <= x"0000";
        Z_4 <= x"0000";
        wait for 100 ns;
        X_1 <= x"ffff";
        X_2 <= x"aaaa";
        X_3 <= x"5555";
        X_4 <= x"0000";
        Z_1 <= x"0000";
        Z_2 <= x"0000";
        Z_3 <= x"0000";
        Z_4 <= x"0000";
        wait for 100 ns;
        X_1 <= x"ffff";
        X_2 <= x"aaaa";
        X_3 <= x"5555";
        X_4 <= x"2492";
        Z_1 <= x"0000";
        Z_2 <= x"0000";
        Z_3 <= x"0000";
        Z_4 <= x"0000";
        wait for 100 ns;
        X_1 <= x"ffff";
        X_2 <= x"aaaa";
        X_3 <= x"5555";
        X_4 <= x"2492";
        Z_1 <= x"db6d";
        Z_2 <= x"0000";
        Z_3 <= x"0000";
        Z_4 <= x"0000";
        wait for 100 ns;
        X_1 <= x"ffff";
        X_2 <= x"aaaa";
        X_3 <= x"5555";
        X_4 <= x"2492";
        Z_1 <= x"db6d";
        Z_2 <= x"1c71";
        Z_3 <= x"0000";
        Z_4 <= x"0000";
        wait for 100 ns;
        X_1 <= x"ffff";
        X_2 <= x"aaaa";
        X_3 <= x"5555";
        X_4 <= x"2492";
        Z_1 <= x"db6d";
        Z_2 <= x"1c71";
        Z_3 <= x"cccc";
        Z_4 <= x"0000";
        wait for 100 ns;
        X_1 <= x"ffff";
        X_2 <= x"aaaa";
        X_3 <= x"5555";
        X_4 <= x"2492";
        Z_1 <= x"db6d";
        Z_2 <= x"1c71";
        Z_3 <= x"cccc";
        Z_4 <= x"0002";
        wait for 100 ns;
        assert false report "reached the end of the test";
        wait for 100 ns;
        wait;
		
   end process;

END;

vhdl/trafo.vcd
$date
  Thu May 20 00:18:38 2021
$end
$version
  GHDL v0
$end
$timescale
  1 fs
$end
$scope module standard $end
$upscope $end
$scope module std_logic_1164 $end
$upscope $end
$scope module numeric_std $end
$upscope $end
$scope module tb_trafo $end
$var reg 16 ! x_1[15:0] $end
$var reg 16 " x_2[15:0] $end
$var reg 16 # x_3[15:0] $end
$var reg 16 $ x_4[15:0] $end
$var reg 16 % z_1[15:0] $end
$var reg 16 & z_2[15:0] $end
$var reg 16 ' z_3[15:0] $end
$var reg 16 ( z_4[15:0] $end
$var reg 16 ) y_1[15:0] $end
$var reg 16 * y_2[15:0] $end
$var reg 16 + y_3[15:0] $end
$var reg 16 , y_4[15:0] $end
$scope module uut $end
$var reg 16 - x_1[15:0] $end
$var reg 16 . x_2[15:0] $end
$var reg 16 / x_3[15:0] $end
$var reg 16 0 x_4[15:0] $end
$var reg 16 1 z_1[15:0] $end
$var reg 16 2 z_2[15:0] $end
$var reg 16 3 z_3[15:0] $end
$var reg 16 4 z_4[15:0] $end
$var reg 16 5 y_1[15:0] $end
$var reg 16 6 y_2[15:0] $end
$var reg 16 7 y_3[15:0] $end
$var reg 16 8 y_4[15:0] $end
$scope module cmul_1 $end
$var reg 16 9 i_1[15:0] $end
$var reg 16 : i_2[15:0] $end
$var reg 16 ; o_1[15:0] $end
$var reg 33 < tmp_mul_result[32:0] $end
$var reg 17 = tmp_div_result[16:0] $end
$var reg 16 > tmp_mod_result[15:0] $end
$upscope $end
$scope module cmul_2 $end
$var reg 16 ? i_1[15:0] $end
$var reg 16 @ i_2[15:0] $end
$var reg 16 A o_1[15:0] $end
$var reg 33 B tmp_mul_result[32:0] $end
$var reg 17 C tmp_div_result[16:0] $end
$var reg 16 D tmp_mod_result[15:0] $end
$upscope $end
$scope module cadd_1 $end
$var reg 16 E i_1[15:0] $end
$var reg 16 F i_2[15:0] $end
$var reg 16 G o_1[15:0] $end
$upscope $end
$scope module cadd_2 $end
$var reg 16 H i_1[15:0] $end
$var reg 16 I i_2[15:0] $end
$var reg 16 J o_1[15:0] $end
$upscope $end
$upscope $end
$upscope $end
$enddefinitions $end
#0
bUUUUUUUUUUUUUUUU !
bUUUUUUUUUUUUUUUU "
bUUUUUUUUUUUUUUUU #
bUUUUUUUUUUUUUUUU $
bUUUUUUUUUUUUUUUU %
bUUUUUUUUUUUUUUUU &
bUUUUUUUUUUUUUUUU '
bUUUUUUUUUUUUUUUU (
bXXXXXXXXXXXXXXXX )
bXXXXXXXXXXXXXXXX *
bXXXXXXXXXXXXXXXX +
bXXXXXXXXXXXXXXXX ,
bUUUUUUUUUUUUUUUU -
bUUUUUUUUUUUUUUUU .
bUUUUUUUUUUUUUUUU /
bUUUUUUUUUUUUUUUU 0
bUUUUUUUUUUUUUUUU 1
bUUUUUUUUUUUUUUUU 2
bUUUUUUUUUUUUUUUU 3
bUUUUUUUUUUUUUUUU 4
bXXXXXXXXXXXXXXXX 5
bXXXXXXXXXXXXXXXX 6
bXXXXXXXXXXXXXXXX 7
bXXXXXXXXXXXXXXXX 8
bUUUUUUUUUUUUUUUU 9
bUUUUUUUUUUUUUUUU :
bXXXXXXXXXXXXXXXX ;
bXXXXXXXXXXXXXXXXXXXXXXXXXXXXXXXXX <
bXXXXXXXXXXXXXXXXX =
bXXXXXXXXXXXXXXXX >
bUUUUUUUUUUUUUUUU ?
bUUUUUUUUUUUUUUUU @
bXXXXXXXXXXXXXXXX A
bXXXXXXXXXXXXXXXXXXXXXXXXXXXXXXXXX B
bXXXXXXXXXXXXXXXXX C
bXXXXXXXXXXXXXXXX D
bUUUUUUUUUUUUUUUU E
bUUUUUUUUUUUUUUUU F
bXXXXXXXXXXXXXXXX G
bUUUUUUUUUUUUUUUU H
bUUUUUUUUUUUUUUUU I
bXXXXXXXXXXXXXXXX J
#100000000
b0000000000000000 !
b0000000000000000 "
b0000000000000000 #
b0000000000000000 $
b0000000000000000 %
b0000000000000000 &
b0000000000000000 '
b0000000000000000 (
b0000000000000001 )
b0000000000000000 *
b0000000000000000 +
b0000000000000001 ,
b0000000000000000 -
b0000000000000000 .
b0000000000000000 /
b0000000000000000 0
b0000000000000000 1
b0000000000000000 2
b0000000000000000 3
b0000000000000000 4
b0000000000000001 5
b0000000000000000 6
b0000000000000000 7
b0000000000000001 8
b0000000000000000 9
b0000000000000000 :
b0000000000000001 ;
b100000000000000000000000000000000 <
b10000000000000000 =
b0000000000000000 >
b0000000000000000 ?
b0000000000000000 @
b0000000000000001 A
b100000000000000000000000000000000 B
b10000000000000000 C
b0000000000000000 D
b0000000000000000 E
b0000000000000000 F
b0000000000000000 G
b0000000000000000 H
b0000000000000000 I
b0000000000000000 J
#200000000
b1111111111111111 !
b0000000000000010 )
b1111111111111111 -
b0000000000000010 5
b1111111111111111 9
b0000000000000010 ;
b011111111111111110000000000000000 <
b01111111111111111 =
#300000000
b1010101010101010 "
b1010101010101010 +
b1010101010101010 .
b1010101010101010 7
b1010101010101010 H
b1010101010101010 J
#400000000
b0101010101010101 #
b0101010101010101 *
b0101010101010101 /
b0101010101010101 6
b0101010101010101 E
b0101010101010101 G
#500000000
b0010010010010010 $
b1101101101101111 ,
b0010010010010010 0
b1101101101101111 8
b0010010010010010 ?
b1101101101101111 A
b000100100100100100000000000000000 B
b00010010010010010 C
#600000000
b1101101101101101 %
b0100100100101000 )
b1101101101101101 1
b0100100100101000 5
b1101101101101101 :
b0100100100101000 ;
b011011011011011000010010010010011 <
b01101101101101100 =
b0010010010010011 >
#700000000
b0001110001110001 &
b0111000111000110 *
b0001110001110001 2
b0111000111000110 6
b0001110001110001 F
b0111000111000110 G
#800000000
b1100110011001100 '
b0111011101110110 +
b1100110011001100 3
b0111011101110110 7
b1100110011001100 I
b0111011101110110 J
#900000000
b0000000000000010 (
b0100100100100100 ,
b0000000000000010 4
b0100100100100100 8
b0000000000000010 @
b0100100100100100 A
b000000000000000000100100100100100 B
b00000000000000000 C
b0100100100100100 D
